{
  "main": {
    "id": "01960df463ca4612",
    "type": "split",
    "children": [
      {
        "id": "dbdbd746d5fbed5b",
        "type": "tabs",
        "children": [
          {
            "id": "0e78baf5e70ff508",
            "type": "leaf",
            "state": {
              "type": "markdown",
              "state": {
                "file": "VLA/Diffusion-robotics/README.md",
                "mode": "source",
                "source": false
              },
              "icon": "lucide-file",
              "title": "README"
            }
          }
        ]
      }
    ],
    "direction": "vertical"
  },
  "left": {
    "id": "df607af02b73ce05",
    "type": "split",
    "children": [
      {
        "id": "33459aa91bdd665b",
        "type": "tabs",
        "children": [
          {
            "id": "84d38cc92cfe1985",
            "type": "leaf",
            "state": {
              "type": "file-explorer",
              "state": {
                "sortOrder": "alphabetical",
                "autoReveal": false
              },
              "icon": "lucide-folder-closed",
              "title": "Files"
            }
          },
          {
            "id": "298f436da62d9200",
            "type": "leaf",
            "state": {
              "type": "search",
              "state": {
                "query": "",
                "matchingCase": false,
                "explainSearch": false,
                "collapseAll": false,
                "extraContext": false,
                "sortOrder": "alphabetical"
              },
              "icon": "lucide-search",
              "title": "Search"
            }
          },
          {
            "id": "e1d3511acc6ddcc9",
            "type": "leaf",
            "state": {
              "type": "bookmarks",
              "state": {},
              "icon": "lucide-bookmark",
              "title": "Bookmarks"
            }
          }
        ]
      }
    ],
    "direction": "horizontal",
    "width": 300
  },
  "right": {
    "id": "879e2908d6eb3d8d",
    "type": "split",
    "children": [
      {
        "id": "2827486aa882d0e3",
        "type": "tabs",
        "children": [
          {
            "id": "a123bab26ce2afbe",
            "type": "leaf",
            "state": {
              "type": "backlink",
              "state": {
                "file": "VLA/Diffusion-robotics/README.md",
                "collapseAll": false,
                "extraContext": false,
                "sortOrder": "alphabetical",
                "showSearch": false,
                "searchQuery": "",
                "backlinkCollapsed": false,
                "unlinkedCollapsed": true
              },
              "icon": "links-coming-in",
              "title": "Backlinks for README"
            }
          },
          {
            "id": "fe362c06eeb3644a",
            "type": "leaf",
            "state": {
              "type": "outgoing-link",
              "state": {
                "file": "VLA/Diffusion-robotics/README.md",
                "linksCollapsed": false,
                "unlinkedCollapsed": true
              },
              "icon": "links-going-out",
              "title": "Outgoing links from README"
            }
          },
          {
            "id": "f5e28024201cf1e6",
            "type": "leaf",
            "state": {
              "type": "tag",
              "state": {
                "sortOrder": "frequency",
                "useHierarchy": true,
                "showSearch": false,
                "searchQuery": ""
              },
              "icon": "lucide-tags",
              "title": "Tags"
            }
          },
          {
            "id": "1c59f595dce97193",
            "type": "leaf",
            "state": {
              "type": "all-properties",
              "state": {
                "sortOrder": "frequency",
                "showSearch": false,
                "searchQuery": ""
              },
              "icon": "lucide-archive",
              "title": "All properties"
            }
          },
          {
            "id": "0baa8f038419021c",
            "type": "leaf",
            "state": {
              "type": "outline",
              "state": {
                "file": "VLA/Diffusion-robotics/README.md",
                "followCursor": false,
                "showSearch": false,
                "searchQuery": ""
              },
              "icon": "lucide-list",
              "title": "Outline of README"
            }
          }
        ]
      }
    ],
    "direction": "horizontal",
    "width": 300,
    "collapsed": true
  },
  "left-ribbon": {
    "hiddenItems": {
      "switcher:Open quick switcher": false,
      "graph:Open graph view": false,
      "canvas:Create new canvas": false,
      "daily-notes:Open today's daily note": false,
      "templates:Insert template": false,
      "command-palette:Open command palette": false,
      "bases:Create new base": false
    }
  },
  "active": "0e78baf5e70ff508",
  "lastOpenFiles": [
    "VLA/Diffusion-robotics/diffusion_policy_ijrr.pdf",
    "VLA/Diffusion-robotics/2205.09991v2.pdf",
    "VLA/Diffusion-robotics/2504.08438v3.pdf",
    "VLA/safety/zhang2025-safevla-report.md",
    "VLA/safety/zhang2025-safevla-architecture.html",
    "VLA/safety/xiao2026-worldenv-report.md",
    "VLA/safety/xiao2026-worldenv-architecture.html",
    "VLA/safety/tang2026-safedojo-report.md",
    "VLA/safety/tang2026-safedojo-architecture.html",
    "VLA/safety/README.md",
    "VLA/safety/li2026-vla-safety-taxonomy.html",
    "VLA/safety/li2026-vla-safety-report.md",
    "VLA/safety/li2026-vla-safety-dualloop.html",
    "VLA/safety/hu2026-vlesa-report.md",
    "VLA/safety/hu2026-vlesa-architecture.html",
    "VLA/safety/2606.20698v1.pdf",
    "VLA/safety/2606.03954v1.pdf",
    "VLA-guardrails/tang2026-safedojo-report.md",
    "VLA/Diffusion-robotics/README.md",
    "VLA/worldmodels/zhang2025-safevla-report.md",
    "VLA/worldmodels/xiao2026-worldenv-report.md",
    "VLA/worldmodels/tang2026-safedojo-report.md",
    "VLA/worldmodels/README.md",
    "VLA/worldmodels/li2026-vla-safety-report.md",
    "VLA/worldmodels/hu2026-vlesa-report.md",
    "VLA-guardrails/zhang2025-safevla-report.md",
    "VLA-guardrails/xiao2026-worldenv-report.md",
    "openwiki/architecture/workflow_and_architecture.md"
  ]
}